colcon_gha_visualize/__init__.py
colcon_gha_visualize/handlers.py
colcon_gha_visualize/mermaid_generator.py
colcon_gha_visualize-0.1.0.dist-info/METADATA
colcon_gha_visualize-0.1.0.dist-info/WHEEL
colcon_gha_visualize-0.1.0.dist-info/entry_points.txt
colcon_gha_visualize-0.1.0.dist-info/licenses/LICENSE
colcon_gha_visualize-0.1.0.dist-info/RECORD
