Metadata-Version: 2.4
Name: colcon-gha-visualize
Version: 0.1.0
Summary: Add your description here
License-File: LICENSE
Keywords: colcon
Requires-Python: >=3.8
Requires-Dist: colcon-common-extensions>=0.3.0
Requires-Dist: colcon-core>=0.20.1
